[{
    "name": "系统管理",
    "url": "main.system",
    "children": [{
        "name": "用户管理",
        "url": "main.system.user"
    }, {
        "name": "角色管理",
        "url": "main.system.role"
    }, {
        "name": "菜单管理",
        "url": "main.system.menu"
    }, {
        "name": "权限管理",
        "url": "main.system.author"
    }]

},{
    "name": "业务管理",
    "url": "main.business",
    "children": [{
        "name": "项目管理",
        "url": "main.business.project"
    }, {
        "name": "日志管理",
        "url": "main.business.log"
    }]

}]
